lyykline_qt
