Metadata-Version: 2.1
Name: lyykline_qt
Version: 1.4
Summary: lyykline_qt for lyy
Author: lyy
Author-email: 
License: MIT
License-File: LICENSE
